{
    "version": "https://jsonfeed.org/version/1",
    "title": "Unofficial Skills",
    "description": "",
    "home_page_url": "https://skills.andrewstech.me",
    "feed_url": "https://skills.andrewstech.me/feed.json",
    "user_comment": "",
    "icon": "https://skills.andrewstech.me/media/website/favicon.ico",
    "author": {
        "name": "andrews tech"
    },
    "items": [
        {
            "id": "https://skills.andrewstech.me/watch-this-space/",
            "url": "https://skills.andrewstech.me/watch-this-space/",
            "title": "Watch this space",
            "summary": "Over the next few days I will start uploading custom built skills made by the community for both google and alexa. Tutorials and setup links will be uploaded here. If you have a skill that you would like to be featured then email: skills@andrewstech.me ",
            "content_html": "<p>Over the next few days I will start uploading custom built skills made by the community for both google and alexa. Tutorials and setup links will be uploaded here.</p>\n<p>If you have a skill that you would like to be featured then email: skills@andrewstech.me</p>\n<p> </p>",
            "author": {
                "name": "andrews tech"
            },
            "tags": [
            ],
            "date_published": "2020-03-17T16:07:43+00:00",
            "date_modified": "2020-03-17T18:29:39+00:00"
        }
    ]
}
